{
    "1": {
        "name": "Ryan",
        "spriteKey": "ryan",
        "facing": 0,
        "description": "This is the npc that lives in `room`.  He's hacking away at the computer.  He's part of a small quest-line to get Lo's hearing aids and USB.",
        "interaction": [{
            "id": 1,
            "flags": [500]

        }],
        "dialog": [{
                "id": 34,
                "flags": [507],
                "default": false
            },
            {
                "id": 31,
                "flags": [505],
                "default": false
            },
            {
                "id": 29,
                "flags": [503],
                "default": false
            },
            {
                "id": 27,
                "flags": [500, 501],
                "default": false
            },
            {
                "id": 26,
                "flags": [501],
                "default": false
            },
            {
                "id": 25,
                "flags": [],
                "default": true
            }
        ],
        "placement": [{
            "x": 192,
            "y": 128,
            "default": true,
            "flags": []
        }]
    },
    "2": {
        "name": "Laundromancer",
        "spriteKey": "laundromancer-sprite",
        "description": "This is the first boss of the first dungeon.  Defeating him yields a silver key, which you can use to open doors.",
        "dialog": [{
            "id": 28,
            "flags": [],
            "default": true
        }],
        "placement": [{
                "x": 256,
                "y": 1216,
                "default": true,
                "flags": []
            },
            {
                "x": null,
                "y": null,
                "default": false,
                "flags": [502]
            }
        ],
        "encounterId": 700


    },
    "3": {
        "name": "Wanmonster",
        "spriteKey": "wanmonster-sprite",
        "description": "This is the first boss of the first dungeon.  Defeating him yields a silver key, which you can use to open doors.",
        "dialog": [{
            "id": 30,
            "flags": [],
            "default": true
        }],
        "placement": [{
                "x": 256,
                "y": 320,
                "default": true,
                "flags": []
            },
            {
                "x": null,
                "y": null,
                "default": false,
                "flags": [504]
            }
        ],
        "encounterId": 701

    },
    "4": {
        "name": "Cosmoknight",
        "spriteKey": "cosmoknight-sprite",
        "description": "This is the third boss of the dungeon.  Defeating him yields a silver key, which you can use to open doors.",
        "dialog": [{
            "id": 33,
            "flags": [],
            "default": true
        }],
        "placement": [{
                "x": 4096,
                "y": 1152,
                "default": true,
                "flags": []
            },
            {
                "x": null,
                "y": null,
                "default": false,
                "flags": [506]
            }
        ],
        "encounterId": 702

    },
    "5": {
        "name": "Dave",
        "spriteKey": "dave",
        "description": "It's just dave.",
        "facing": 1,
        "interaction": [{
            "id": 1,
            "flags": []

        }],
        "dialog": [{
            "id": 41,
            "flags": [],
            "default": true
        }],
        "placement": [{
            "x": 576,
            "y": 384,
            "default": true,
            "flags": []
        }]
    }
}